{
  "veiculos": [
    {
      "id": "9812",
      "modelo": "Dale",
      "marca": {
        "id": 7,
        "nome": "Toyota"
      },
      "tipo": {
        "id": 2,
        "nome": "Sedan"
      },
      "placa": "UJD9876",
      "cor": "Preto",
      "nomeProprietario": "Pretinho",
      "contatoProprietario": "66 753526784"
    }
  ],
  "vagas": [
    {
      "id": "4e06",
      "codigo": "74",
      "coberta": true
    },
    {
      "id": "123",
      "codigo": "71",
      "coberta": true
    }
  ],
  "vagasOcupadas": [
    {
      "id": "6729",
      "veiculoId": "9812",
      "vagaId": "4e06",
      "horaInicio": "2025-05-20T21:15:00",
      "precoHora": 8
    }
  ]
}